ChangeLog
GoodTests.py
LICENSE
MANIFEST.in
README.md
README.rst
install.sh
setup.py
test_Magic.py
GoodTests.egg-info/PKG-INFO
GoodTests.egg-info/SOURCES.txt
GoodTests.egg-info/dependency_links.txt
GoodTests.egg-info/top_level.txt
distrib/README
distrib/runTests.py
distrib/x.py
doc/GoodTests.html