Metadata-Version: 1.2
Name: GoodTests
Version: 3.0.5
Summary: A fast, parallel, featured python unit-testing framework
Home-page: https://github.com/kata198/GoodTests
Author: Tim Savannah
Author-email: kata198@gmail.com
Maintainer: Tim Savannah
Maintainer-email: kata198@gmail.com
License: LGPLv2
Keywords: unit test,python,good tests,parallel,fast,framework,testing,py.test,nose,unit
Platform: UNKNOWN
Classifier: Development Status :: 6 - Mature
Classifier: Programming Language :: Python
Classifier: License :: OSI Approved :: GNU Lesser General Public License v2 (LGPLv2)
Classifier: Programming Language :: Python :: 2
Classifier: Programming Language :: Python :: 2
Classifier: Programming Language :: Python :: 2.6
Classifier: Programming Language :: Python :: 2.7
Classifier: Programming Language :: Python :: 3
Classifier: Programming Language :: Python :: 3.4
Classifier: Programming Language :: Python :: 3.5
Classifier: Programming Language :: Python :: 3.6
Classifier: Programming Language :: Python :: 3.7
Classifier: Topic :: Software Development :: Testing
Provides: GoodTests
